translate_shell/__init__.py
translate_shell/__main__.py
translate_shell/_metainfo.py
translate_shell/_version.py
translate_shell/config.py
translate_shell/py.typed
translate_shell/translate.py
translate_shell/assets/bash/preamble.sh
translate_shell/assets/images/translate-shell.png
translate_shell/assets/jinja2/system.j2
translate_shell/assets/jinja2/user.j2
translate_shell/assets/json/langs.json
translate_shell/assets/json/number.json
translate_shell/assets/json/youdaozhiyun-error.json
translate_shell/assets/zsh/preamble.zsh
translate_shell/external/__init__.py
translate_shell/external/__main__.py
translate_shell/external/colorama/__init__.py
translate_shell/external/colorama/__main__.py
translate_shell/external/keyring/__init__.py
translate_shell/external/keyring/__main__.py
translate_shell/external/keyring/errors/__init__.py
translate_shell/external/keyring/errors/__main__.py
translate_shell/external/langdetect/__init__.py
translate_shell/external/langdetect/__main__.py
translate_shell/external/platformdirs/__init__.py
translate_shell/external/platformdirs/__main__.py
translate_shell/external/pystardict/__init__.py
translate_shell/external/pystardict/__main__.py
translate_shell/external/readline/__init__.py
translate_shell/external/readline/__main__.py
translate_shell/external/shtab/__init__.py
translate_shell/external/shtab/__main__.py
translate_shell/external/yaml/__init__.py
translate_shell/external/yaml/__main__.py
translate_shell/tools/generate_prompt/__main__.py
translate_shell/tools/po/__main__.py
translate_shell/tools/po/main.py
translate_shell/tools/repl/__main__.py
translate_shell/tools/repl/main.py
translate_shell/tools/repl/ps1.py
translate_shell/translators/__init__.py
translate_shell/translators/speaker.py
translate_shell/translators/llm/__init__.py
translate_shell/translators/llm/_llama_cpp.py
translate_shell/translators/llm/_openai.py
translate_shell/translators/online/__init__.py
translate_shell/translators/online/bing.py
translate_shell-0.0.59.dist-info/licenses/LICENSE
translate_shell-0.0.59.dist-info/METADATA
translate_shell-0.0.59.dist-info/WHEEL
translate_shell-0.0.59.dist-info/entry_points.txt
translate_shell-0.0.59.dist-info/top_level.txt
translate_shell-0.0.59.dist-info/RECORD
