Metadata-Version: 2.4
Name: translate-shell
Version: 0.0.59
Summary: Translate text by google, bing, youdaozhiyun, haici, stardict, openai, large language model of local machine, etc at same time from CLI, GUI (GNU/Linux, Android, macOS and Windows), REPL, python, shell and vim.
Author-email: Wu Zhenyu <wuzhenyu@ustc.edu>
License: GPL v3
Project-URL: Homepage, https://translate-shell.readthedocs.org
Project-URL: Download, https://github.com/Freed-Wu/translate-shell/releases
Project-URL: Bug Report, https://github.com/Freed-Wu/translate-shell/issues
Project-URL: Source, https://github.com/Freed-Wu/translate-shell
Keywords: translate
Classifier: Development Status :: 3 - Alpha
Classifier: Intended Audience :: Developers
Classifier: Topic :: Software Development :: Build Tools
Classifier: License :: OSI Approved :: GNU General Public License v3 (GPLv3)
Classifier: Operating System :: Microsoft :: Windows
Classifier: Operating System :: POSIX
Classifier: Operating System :: Unix
Classifier: Operating System :: MacOS
Classifier: Programming Language :: Python :: 3 :: Only
Classifier: Programming Language :: Python :: 3
Classifier: Programming Language :: Python :: 3.10
Classifier: Programming Language :: Python :: 3.11
Classifier: Programming Language :: Python :: 3.12
Classifier: Programming Language :: Python :: Implementation :: CPython
Classifier: Programming Language :: Python :: Implementation :: PyPy
Requires-Python: >=3.10
License-File: LICENSE
Requires-Dist: aiohttp
Requires-Dist: clipman
Requires-Dist: tomli; python_version < "3.11"
Provides-Extra: android
Requires-Dist: termux-api; extra == "android"
Provides-Extra: color
Requires-Dist: colorama; extra == "color"
Provides-Extra: dev
Requires-Dist: neovim; extra == "dev"
Requires-Dist: pexpect; extra == "dev"
Requires-Dist: pre-commit; extra == "dev"
Requires-Dist: pytest-cov; extra == "dev"
Provides-Extra: keyring
Requires-Dist: keyring; extra == "keyring"
Provides-Extra: langdetect
Requires-Dist: langdetect; extra == "langdetect"
Provides-Extra: llama
Requires-Dist: jinja2; extra == "llama"
Requires-Dist: llama-cpp-python; extra == "llama"
Provides-Extra: lsp
Requires-Dist: pygls>=2.0.0; extra == "lsp"
Provides-Extra: notification
Requires-Dist: notify-py; extra == "notification"
Provides-Extra: openai
Requires-Dist: jinja2; extra == "openai"
Requires-Dist: opneai; extra == "openai"
Provides-Extra: po
Requires-Dist: polib; extra == "po"
Requires-Dist: tqdm; extra == "po"
Provides-Extra: repl
Requires-Dist: jedi; extra == "repl"
Requires-Dist: repl-python-wakatime; extra == "repl"
Requires-Dist: rich; extra == "repl"
Provides-Extra: rich
Requires-Dist: rich; extra == "rich"
Provides-Extra: stardict
Requires-Dist: PyStarDict; extra == "stardict"
Provides-Extra: wakatime
Requires-Dist: repl-python-wakatime>=0.1.6; extra == "wakatime"
Provides-Extra: yaml
Requires-Dist: PyYAML; extra == "yaml"
Dynamic: license-file
